test_contruct_lib/__init__.py
test_contruct_lib/py.typed
test_contruct_lib/_jsii/__init__.py
test_contruct_lib/_jsii/test-contruct-lib@0.1.1.jsii.tgz
test_contruct_lib-0.1.1.dist-info/LICENSE
test_contruct_lib-0.1.1.dist-info/METADATA
test_contruct_lib-0.1.1.dist-info/WHEEL
test_contruct_lib-0.1.1.dist-info/top_level.txt
test_contruct_lib-0.1.1.dist-info/RECORD
